<?xml version="1.0" encoding="UTF-8" ?>
<odoo>

    <!-- Purchase View Inherit -->
    <record id="view_purchase_form_inherit" model="ir.ui.view">
        <field name="name">purchase.form.view.inherit</field>
        <field name="model">purchase.order</field>
        <field name="inherit_id" ref="purchase.purchase_order_form"/>
        <field name="arch" type="xml">
            <field name="incoterm_id" position="after">
                <field name="create_api_values" readonly="1"/>
            </field>
        </field>
    </record>

</odoo>
